codigest/__init__.py
codigest/__main__.py
codigest/config.py
codigest/main.py
codigest/commands/diff.py
codigest/commands/digest.py
codigest/commands/init.py
codigest/commands/scan.py
codigest/commands/semdiff.py
codigest/commands/tree.py
codigest/core/git_ops.py
codigest/core/processor.py
codigest/core/prompts.py
codigest/core/resolver.py
codigest/core/scanner.py
codigest/core/semdiff.py
codigest/core/shadow.py
codigest/core/structure.py
codigest/core/tags.py
codigest/core/tokenizer.py
codigest-0.3.3.dist-info/METADATA
codigest-0.3.3.dist-info/WHEEL
codigest-0.3.3.dist-info/entry_points.txt
codigest-0.3.3.dist-info/RECORD
