Metadata-Version: 2.4
Name: codigest
Version: 0.3.3
Summary: Human-Centered Codebase Context Manager for LLMs
Project-URL: Homepage, https://github.com/SJB777/codigest
Project-URL: Repository, https://github.com/SJB777/codigest
Project-URL: Issues, https://github.com/SJB777/codigest/issues
Author-email: Codigest Team <sngd024@google.com>
License: MIT
Classifier: Intended Audience :: Developers
Classifier: License :: OSI Approved :: MIT License
Classifier: Operating System :: OS Independent
Classifier: Programming Language :: Python :: 3
Classifier: Programming Language :: Python :: 3.14
Classifier: Topic :: Software Development :: Libraries :: Python Modules
Classifier: Topic :: Utilities
Requires-Python: >=3.14
Requires-Dist: loguru
Requires-Dist: pathspec
Requires-Dist: pyperclip
Requires-Dist: rich
Requires-Dist: tomli-w
Requires-Dist: typer
